Metadata-Version: 2.1
Name: ternaus-cleantext
Version: 0.0.1
Summary: Clean text from extra spaces and special symbols as in the CLIP model.
Home-page: https://github.com/ternaus/ternaus-cleantext
Author: Vladimir Iglovikov
License: MIT
Classifier: License :: OSI Approved :: MIT License
Classifier: Intended Audience :: Developers
Classifier: Intended Audience :: Science/Research
Classifier: Operating System :: OS Independent
Classifier: Programming Language :: Python
Classifier: Programming Language :: Python :: 3
Classifier: Topic :: Software Development :: Libraries
Classifier: Topic :: Software Development :: Libraries :: Python Modules
License-File: LICENSE
